{
  "id": "intro",
  "title": "Welcome",
  "description": "This website is a collection of notes, tips and tricks that I've collected over the years. It mainly focusses on Linux, software, coding, programming and other computer related topics. It is a second brain, if you will. Feel free to use it for your own purposes. If you have any suggestions, questions or other feedback, please let me know.",
  "source": "@site/docs/intro.md",
  "sourceDirName": ".",
  "slug": "/",
  "permalink": "/",
  "draft": false,
  "unlisted": false,
  "editUrl": "https://codeberg.org/jorisvandijk/joriscodes/src/branch/main/docs/intro.md",
  "tags": [],
  "version": "current",
  "lastUpdatedBy": "Author",
  "lastUpdatedAt": 1539502055000,
  "sidebarPosition": 1,
  "frontMatter": {
    "slug": "/",
    "sidebar_position": 1
  },
  "sidebar": "docsSidebar",
  "next": {
    "title": "Linux",
    "permalink": "/category/linux"
  }
}